[0, [{"class": "const", "name": "BestCompression", "type": ""}, {"class": "const", "name": "BestSpeed", "type": ""}, {"class": "const", "name": "DefaultCompression", "type": ""}, {"class": "const", "name": "NoCompression", "type": ""}, {"class": "func", "name": "Decode", "type": "func(r io.Reader) (image.Image, error)"}, {"class": "func", "name": "DecodeConfig", "type": "func(r io.Reader) (image.Config, error)"}, {"class": "func", "name": "Encode", "type": "func(w io.Writer, m image.Image) error"}, {"class": "type", "name": "CompressionLevel", "type": "int"}, {"class": "type", "name": "Encoder", "type": "struct"}, {"class": "type", "name": "FormatError", "type": "string"}, {"class": "type", "name": "UnsupportedError", "type": "string"}]]